xf_build/__init__.py
xf_build/api.py
xf_build/build.py
xf_build/env.py
xf_build/log.py
xf_build/menuconfig.py
xf_build/plugins.py
xf_build/plugins_hookspec.py
xf_build/cmd/__init__.py
xf_build/cmd/cmd.py
xf_build/cmd/package.py
xf_build/cmd/project.py
xf_build-0.4.2.dist-info/LICENSE
xf_build-0.4.2.dist-info/METADATA
xf_build-0.4.2.dist-info/WHEEL
xf_build-0.4.2.dist-info/entry_points.txt
xf_build-0.4.2.dist-info/top_level.txt
xf_build-0.4.2.dist-info/RECORD
