Metadata-Version: 2.1
Name: xf_build
Version: 0.4.2
Summary: A tools for xfusion
Home-page: http://www.coral-zone.cc/
Author: kirto
Author-email: sky.kirto@qq.com
Classifier: Programming Language :: Python :: 3
Classifier: License :: OSI Approved :: MIT License
Requires-Python: >=3.6
License-File: LICENSE
Requires-Dist: jinja2
Requires-Dist: kconfiglib
Requires-Dist: requests
Requires-Dist: rich
Requires-Dist: art
Requires-Dist: pyserial
